utflib/__init__.py
utflib/table_chars.py
utflib-0.0.2.dist-info/LICENSE
utflib-0.0.2.dist-info/METADATA
utflib-0.0.2.dist-info/WHEEL
utflib-0.0.2.dist-info/top_level.txt
utflib-0.0.2.dist-info/RECORD
