Metadata-Version: 2.1
Name: utflib
Version: 0.0.2
Summary: Library for accessing readably named UTF characters.
Home-page: https://github.com/TravisLazar/utflib
Author: Travis Lazar
Author-email: travis.lazar@gmail.com
License: GPLv3
Platform: UNKNOWN
Classifier: Programming Language :: Python :: 3
